<DOMSymbolItem xmlns:xsi="http://www.w3.org/2001/XMLSchema-instance" xmlns="http://ns.adobe.com/xfl/2008/" name="InfoIndicatorSmallView" itemID="65c20e71-00001fcd" linkageExportForAS="true" linkageIdentifier="InfoIndicatorSmallView" linkageClassName="InfoIndicatorSmallView" lastModified="1707216497">
  <timeline>
    <DOMTimeline name="InfoIndicatorSmallView">
      <layers>
        <DOMLayer name="Layer 1" color="#CC44FD">
          <frames>
            <DOMFrame index="0" keyMode="9728">
              <elements>
                <DOMSymbolInstance libraryItemName="iconsAll40x40View" name="valueIcon" centerPoint3DX="56" centerPoint3DY="51">
                  <matrix>
                    <Matrix tx="36" ty="31"/>
                  </matrix>
                  <transformationPoint>
                    <Point/>
                  </transformationPoint>
                </DOMSymbolInstance>
              </elements>
            </DOMFrame>
          </frames>
        </DOMLayer>
        <DOMLayer name="Layer 2" color="#62DF4B">
          <frames>
            <DOMFrame index="0" keyMode="9728">
              <elements>
                <DOMDynamicText name="title" fontRenderingMode="standard" width="229.5" height="120" isSelectable="false" renderAsHTML="true" lineType="multiline">
                  <matrix>
                    <Matrix tx="65" ty="9"/>
                  </matrix>
                  <textRuns>
                    <DOMTextRun>
                      <characters></characters>
                      <textAttrs>
                        <DOMTextAttrs aliasText="false" autoKern="false" rotation="true" lineHeight="13.35"/>
                      </textAttrs>
                    </DOMTextRun>
                  </textRuns>
                </DOMDynamicText>
              </elements>
            </DOMFrame>
          </frames>
        </DOMLayer>
        <DOMLayer name="Layer 3" color="#F2A3DC" current="true" isSelected="true">
          <frames>
            <DOMFrame index="0" keyMode="9728">
              <elements>
                <DOMSymbolInstance libraryItemName="Symbol 1056" name="darkBg" centerPoint3DX="53" centerPoint3DY="50">
                  <matrix>
                    <Matrix a="3.45001220703125" d="0.620010375976562" tx="3"/>
                  </matrix>
                  <transformationPoint>
                    <Point/>
                  </transformationPoint>
                </DOMSymbolInstance>
              </elements>
            </DOMFrame>
          </frames>
        </DOMLayer>
      </layers>
    </DOMTimeline>
  </timeline>
</DOMSymbolItem>