<DOMSymbolItem xmlns:xsi="http://www.w3.org/2001/XMLSchema-instance" xmlns="http://ns.adobe.com/xfl/2008/" name="ListContainerHeadlineVerticalView" itemID="65c20e4c-00001fb4" linkageExportForAS="true" linkageIdentifier="ListContainerHeadlineVerticalView" linkageClassName="ListContainerHeadlineVerticalView" lastModified="1707216460">
  <timeline>
    <DOMTimeline name="ListContainerHeadlineVerticalView">
      <layers>
        <DOMLayer name="Layer 1" color="#DD4D7A">
          <frames>
            <DOMFrame index="0" keyMode="9728">
              <elements>
                <DOMDynamicText name="title" fontRenderingMode="standard" width="196" height="28.75" renderAsHTML="true">
                  <matrix>
                    <Matrix tx="-208" ty="2"/>
                  </matrix>
                  <textRuns>
                    <DOMTextRun>
                      <characters></characters>
                      <textAttrs>
                        <DOMTextAttrs alignment="right" aliasText="false" autoKern="false" rotation="true" lineHeight="13.35"/>
                      </textAttrs>
                    </DOMTextRun>
                  </textRuns>
                </DOMDynamicText>
              </elements>
            </DOMFrame>
          </frames>
        </DOMLayer>
        <DOMLayer name="Layer 2" color="#C2BE2C" current="true" isSelected="true">
          <frames>
            <DOMFrame index="0" keyMode="9728">
              <elements>
                <DOMSymbolInstance libraryItemName="MenuLib3_xfl_fla.WhiteSelect_38" name="bg" centerPoint3DX="50" centerPoint3DY="250">
                  <matrix>
                    <Matrix a="0.02001953125" d="4.0008544921875" ty="200"/>
                  </matrix>
                  <transformationPoint>
                    <Point/>
                  </transformationPoint>
                </DOMSymbolInstance>
              </elements>
            </DOMFrame>
          </frames>
        </DOMLayer>
      </layers>
    </DOMTimeline>
  </timeline>
</DOMSymbolItem>