<DOMSymbolItem xmlns:xsi="http://www.w3.org/2001/XMLSchema-instance" xmlns="http://ns.adobe.com/xfl/2008/" name="Symbol 2608" itemID="65ccaac0-00002979" lastModified="1707910009">
  <timeline>
    <DOMTimeline name="Symbol 2608">
      <layers>
        <DOMLayer name="Layer 1" color="#9B9DF1">
          <frames>
            <DOMFrame index="0" keyMode="9728">
              <elements>
                <DOMSymbolInstance libraryItemName="Symbol 503" name="icon" centerPoint3DX="51" centerPoint3DY="139">
                  <matrix>
                    <Matrix a="0.789474487304688" d="0.789474487304688" tx="31" ty="119"/>
                  </matrix>
                  <transformationPoint>
                    <Point/>
                  </transformationPoint>
                </DOMSymbolInstance>
              </elements>
            </DOMFrame>
          </frames>
        </DOMLayer>
        <DOMLayer name="Layer 2" color="#C5794F">
          <frames>
            <DOMFrame index="0" keyMode="9728">
              <elements>
                <DOMSymbolInstance libraryItemName="Symbol 503" name="icon2" centerPoint3DX="164" centerPoint3DY="139">
                  <matrix>
                    <Matrix a="0.789474487304688" d="0.789474487304688" tx="144" ty="119"/>
                  </matrix>
                  <transformationPoint>
                    <Point/>
                  </transformationPoint>
                </DOMSymbolInstance>
              </elements>
            </DOMFrame>
          </frames>
        </DOMLayer>
        <DOMLayer name="Layer 3" color="#4D85ED" locked="true" layerType="mask">
          <frames>
            <DOMFrame index="0" keyMode="9728">
              <elements>
                <DOMSymbolInstance libraryItemName="Symbol 11" name="imageMask" centerPoint3DX="138" centerPoint3DY="112">
                  <matrix>
                    <Matrix a="1.65000915527344" d="1.64999389648438" tx="88" ty="62"/>
                  </matrix>
                  <transformationPoint>
                    <Point/>
                  </transformationPoint>
                </DOMSymbolInstance>
              </elements>
            </DOMFrame>
          </frames>
        </DOMLayer>
        <DOMLayer name="Layer 4" color="#FA11D0" parentLayerIndex="2" locked="true">
          <frames>
            <DOMFrame index="0" keyMode="9728">
              <elements>
                <DOMSymbolInstance libraryItemName="Symbol 15" name="image" centerPoint3DX="6" centerPoint3DY="-20">
                  <matrix>
                    <Matrix tx="6" ty="-20"/>
                  </matrix>
                  <transformationPoint>
                    <Point/>
                  </transformationPoint>
                </DOMSymbolInstance>
              </elements>
            </DOMFrame>
          </frames>
        </DOMLayer>
        <DOMLayer name="Layer 5" color="#CA95D6">
          <frames>
            <DOMFrame index="0" keyMode="9728">
              <elements>
                <DOMSymbolInstance libraryItemName="Symbol 14" name="tileDarkBg" centerPoint3DX="138" centerPoint3DY="112">
                  <matrix>
                    <Matrix a="1.65000915527344" d="1.64999389648438" tx="88" ty="62"/>
                  </matrix>
                  <transformationPoint>
                    <Point/>
                  </transformationPoint>
                  <color>
                    <Color alphaMultiplier="0.078125"/>
                  </color>
                </DOMSymbolInstance>
              </elements>
            </DOMFrame>
          </frames>
        </DOMLayer>
        <DOMLayer name="Layer 6" color="#B8B464" current="true" isSelected="true">
          <frames>
            <DOMFrame index="0" keyMode="9728">
              <elements>
                <DOMSymbolInstance libraryItemName="Symbol 11" name="tileBg" centerPoint3DX="138" centerPoint3DY="112">
                  <matrix>
                    <Matrix a="1.75" d="1.75" tx="88" ty="62"/>
                  </matrix>
                  <transformationPoint>
                    <Point/>
                  </transformationPoint>
                  <color>
                    <Color alphaMultiplier="0"/>
                  </color>
                </DOMSymbolInstance>
              </elements>
            </DOMFrame>
          </frames>
        </DOMLayer>
      </layers>
    </DOMTimeline>
  </timeline>
</DOMSymbolItem>