<DOMSymbolItem xmlns:xsi="http://www.w3.org/2001/XMLSchema-instance" xmlns="http://ns.adobe.com/xfl/2008/" name="Symbol 746" itemID="65c1d1f2-00000ccd" lastModified="1707200131">
  <timeline>
    <DOMTimeline name="Symbol 746">
      <layers>
        <DOMLayer name="Layer 1" color="#917690" current="true" isSelected="true">
          <frames>
            <DOMFrame index="0" keyMode="9728">
              <elements>
                <DOMShape isFloating="true">
                  <fills>
                    <FillStyle index="1">
                      <SolidColor color="#FFFFFF"/>
                    </FillStyle>
                  </fills>
                  <edges>
                    <Edge fillStyle0="1" edges="!6 -1605[226 -1605 427 -1520!427 -1520[621 -1438 771 -1288!771 -1288[921 -1138 1003 -944!1003 -944[1088 -743 1088 -523!1088 -523[1088 -370 1046 -223!1046 -223[1004 -77 923 52!923 52[1018 -151 1018 -375!1018 -375[1018 -580 938 -768!938
 -768[861 -950 721 -1090!721 -1090[581 -1230 399 -1307!399 -1307[211 -1387 6 -1387!6 -1387[-200 -1387 -388 -1307!-388 -1307[-569 -1230 -709 -1090!-709 -1090[-850 -950 -927 -768!-927 -768[-1006 -580 -1006 -375!-1006 -375[-1006 -155 -915
 46!-915 46[-993 -80 -1034 -223!-1034 -223[-1076 -369 -1076 -523!-1076 -523[-1076 -743 -991 -944!-991 -944[-909 -1138 -759 -1288!-759 -1288[-609 -1438 -415 -1520!-415 -1520[-214 -1605 6 -1605!6 559[-184 559 -358 486!-358 486[-525 415
 -655 285!-655 285[-784 156 -855 -12!-855 -12[-929 -185 -929 -375!-929 -375[-929 -564 -855 -738!-855 -738[-784 -906 -655 -1035!-655 -1035[-525 -1165 -358 -1236!-358 -1236[-184 -1309 6 -1309!6 -1309[195 -1309 369 -1236!369 -1236[537 -1165
 666 -1035!666 -1035[795 -906 866 -738!866 -738[940 -564 940 -375!940 -375[940 -185 866 -12!866 -12[795 156 666 285!666 285[537 415 369 486!369 486[195 559 6 559!1758 922|1596 811!1596 811|1586 808!1586 808[1580 809 1577 814!1577 814
|1323 1182!1323 1182|1247 1130!1247 1130|1237 1127!1237 1127|1227 1133!1227 1133|1206 1165!1206 1165[1136 1114 1072 1051!1072 1051|1022 996!1022 996[886 823 697 747!697 747[583 702 341 666!341 666|260 654!260 654|159 635!159 635|221 617
!221 617[415 581 586 482!586 482[757 383 886 233!886 233[1022 75 1094 -120!1094 -120[1166 -315 1166 -523!1166 -523[1166 -758 1075 -974!1075 -974[987 -1182 826 -1343!826 -1343[665 -1504 457 -1592!457 -1592[242 -1683 6 -1683!6 -1683[-229
 -1683 -445 -1592!-445 -1592[-653 -1504 -814 -1343!-814 -1343[-975 -1182 -1063 -974!-1063 -974[-1154 -758 -1154 -523!-1154 -523[-1154 -112 -896 206!-896 206[-641 521 -249 609!-249 609|-160 635!-160 635|-261 654!-261 654|-342 666!-342
 666[-584 702 -698 747!-698 747[-887 822 -1023 996!-1023 996|-1073 1050!-1073 1050[-1136 1114 -1207 1165!-1207 1165|-1228 1133!-1228 1133[-1232 1128 -1237 1127!-1237 1127|-1248 1130!-1248 1130|-1324 1182!-1324 1182|-1577 814!-1577 814
|-1586 808!-1586 808|-1597 811!-1597 811|-1759 922!-1759 922|-1765 931!-1765 931|-1762 942!-1762 942|-1151 1830!-1151 1830|-1141 1836!-1141 1836|-1131 1834!-1131 1834|-969 1722!-969 1722|-963 1713!-963 1713|-966 1703!-966 1703|-1219 1335
!-1219 1335|-1143 1283!-1143 1283|-1137 1274!-1137 1274|-1139 1263!-1139 1263|-1162 1229!-1162 1229[-1086 1175 -1018 1106!-1018 1106|-962 1044!-962 1044[-838 886 -667 819!-667 819[-562 777 -330 743!-330 743|-248 731!-248 731[-157 717
 0 677!0 677|248 731!248 731|330 743!330 743[561 777 666 819!666 819[837 886 961 1045!961 1045|1017 1106!1017 1106[1085 1175 1162 1229!1162 1229|1138 1263!1138 1263|1136 1274!1136 1274|1142 1283!1142 1283|1218 1335!1218 1335|965 1703
!965 1703[961 1708 962 1713!962 1713|968 1722!968 1722|1130 1834!1130 1834|1141 1836!1141 1836|1150 1830!1150 1830|1762 942!1762 942|1764 931!1764 931|1758 922"/>
                  </edges>
                </DOMShape>
              </elements>
            </DOMFrame>
          </frames>
        </DOMLayer>
      </layers>
    </DOMTimeline>
  </timeline>
</DOMSymbolItem>