<DOMSymbolItem xmlns:xsi="http://www.w3.org/2001/XMLSchema-instance" xmlns="http://ns.adobe.com/xfl/2008/" name="HUDLib2_xfl_fla.WeaponElementBulletsStaticRegular_291" itemID="65c20fb7-000020a1" lastModified="1707640323">
  <timeline>
    <DOMTimeline name="HUDLib2_xfl_fla.WeaponElementBulletsStaticRegular_291">
      <layers>
        <DOMLayer name="Script Layer" color="#FB998B">
          <frames>
            <DOMFrame index="0" keyMode="9728">
              <Actionscript>
                <script><![CDATA[stop();
]]></script>
              </Actionscript>
              <elements/>
            </DOMFrame>
          </frames>
        </DOMLayer>
        <DOMLayer name="Layer 2" color="#9F71A6">
          <frames>
            <DOMFrame index="0" duration="13" keyMode="9728">
              <elements/>
            </DOMFrame>
            <DOMFrame index="13" keyMode="9728">
              <elements>
                <DOMSymbolInstance libraryItemName="Symbol 3470" symbolType="graphic" loop="loop">
                  <transformationPoint>
                    <Point/>
                  </transformationPoint>
                </DOMSymbolInstance>
              </elements>
            </DOMFrame>
            <DOMFrame index="14" duration="13" keyMode="9728">
              <elements/>
            </DOMFrame>
            <DOMFrame index="27" keyMode="9728">
              <elements>
                <DOMSymbolInstance libraryItemName="Symbol 3483" symbolType="graphic" loop="loop">
                  <transformationPoint>
                    <Point/>
                  </transformationPoint>
                </DOMSymbolInstance>
              </elements>
            </DOMFrame>
            <DOMFrame index="28" duration="13" keyMode="9728">
              <elements/>
            </DOMFrame>
            <DOMFrame index="41" keyMode="9728">
              <elements>
                <DOMSymbolInstance libraryItemName="Symbol 3496" symbolType="graphic" loop="loop">
                  <transformationPoint>
                    <Point/>
                  </transformationPoint>
                </DOMSymbolInstance>
              </elements>
            </DOMFrame>
          </frames>
        </DOMLayer>
        <DOMLayer name="Layer 3" color="#F02DA4">
          <frames>
            <DOMFrame index="0" duration="12" keyMode="9728">
              <elements/>
            </DOMFrame>
            <DOMFrame index="12" keyMode="9728">
              <elements>
                <DOMSymbolInstance libraryItemName="Symbol 3469" symbolType="graphic" loop="loop">
                  <transformationPoint>
                    <Point/>
                  </transformationPoint>
                </DOMSymbolInstance>
              </elements>
            </DOMFrame>
            <DOMFrame index="13" duration="13" keyMode="9728">
              <elements/>
            </DOMFrame>
            <DOMFrame index="26" keyMode="9728">
              <elements>
                <DOMSymbolInstance libraryItemName="Symbol 3482" symbolType="graphic" loop="loop">
                  <transformationPoint>
                    <Point/>
                  </transformationPoint>
                </DOMSymbolInstance>
              </elements>
            </DOMFrame>
            <DOMFrame index="27" duration="13" keyMode="9728">
              <elements/>
            </DOMFrame>
            <DOMFrame index="40" keyMode="9728">
              <elements>
                <DOMSymbolInstance libraryItemName="Symbol 3495" symbolType="graphic" loop="loop">
                  <transformationPoint>
                    <Point/>
                  </transformationPoint>
                </DOMSymbolInstance>
              </elements>
            </DOMFrame>
            <DOMFrame index="41" keyMode="9728">
              <elements/>
            </DOMFrame>
          </frames>
        </DOMLayer>
        <DOMLayer name="Layer 4" color="#23EC83">
          <frames>
            <DOMFrame index="0" duration="11" keyMode="9728">
              <elements/>
            </DOMFrame>
            <DOMFrame index="11" keyMode="9728">
              <elements>
                <DOMSymbolInstance libraryItemName="Symbol 3468" symbolType="graphic" loop="loop">
                  <transformationPoint>
                    <Point/>
                  </transformationPoint>
                </DOMSymbolInstance>
              </elements>
            </DOMFrame>
            <DOMFrame index="12" duration="13" keyMode="9728">
              <elements/>
            </DOMFrame>
            <DOMFrame index="25" keyMode="9728">
              <elements>
                <DOMSymbolInstance libraryItemName="Symbol 3481" symbolType="graphic" loop="loop">
                  <transformationPoint>
                    <Point/>
                  </transformationPoint>
                </DOMSymbolInstance>
              </elements>
            </DOMFrame>
            <DOMFrame index="26" duration="13" keyMode="9728">
              <elements/>
            </DOMFrame>
            <DOMFrame index="39" keyMode="9728">
              <elements>
                <DOMSymbolInstance libraryItemName="Symbol 3494" symbolType="graphic" loop="loop">
                  <transformationPoint>
                    <Point/>
                  </transformationPoint>
                </DOMSymbolInstance>
              </elements>
            </DOMFrame>
            <DOMFrame index="40" duration="2" keyMode="9728">
              <elements/>
            </DOMFrame>
          </frames>
        </DOMLayer>
        <DOMLayer name="Layer 5" color="#2097DE">
          <frames>
            <DOMFrame index="0" duration="10" keyMode="9728">
              <elements/>
            </DOMFrame>
            <DOMFrame index="10" keyMode="9728">
              <elements>
                <DOMSymbolInstance libraryItemName="Symbol 3467" symbolType="graphic" loop="loop">
                  <transformationPoint>
                    <Point/>
                  </transformationPoint>
                </DOMSymbolInstance>
              </elements>
            </DOMFrame>
            <DOMFrame index="11" duration="13" keyMode="9728">
              <elements/>
            </DOMFrame>
            <DOMFrame index="24" keyMode="9728">
              <elements>
                <DOMSymbolInstance libraryItemName="Symbol 3480" symbolType="graphic" loop="loop">
                  <transformationPoint>
                    <Point/>
                  </transformationPoint>
                </DOMSymbolInstance>
              </elements>
            </DOMFrame>
            <DOMFrame index="25" duration="13" keyMode="9728">
              <elements/>
            </DOMFrame>
            <DOMFrame index="38" keyMode="9728">
              <elements>
                <DOMSymbolInstance libraryItemName="Symbol 3493" symbolType="graphic" loop="loop">
                  <transformationPoint>
                    <Point/>
                  </transformationPoint>
                </DOMSymbolInstance>
              </elements>
            </DOMFrame>
            <DOMFrame index="39" duration="3" keyMode="9728">
              <elements/>
            </DOMFrame>
          </frames>
        </DOMLayer>
        <DOMLayer name="Layer 6" color="#F38E97">
          <frames>
            <DOMFrame index="0" duration="9" keyMode="9728">
              <elements/>
            </DOMFrame>
            <DOMFrame index="9" keyMode="9728">
              <elements>
                <DOMSymbolInstance libraryItemName="Symbol 3466" symbolType="graphic" loop="loop">
                  <transformationPoint>
                    <Point/>
                  </transformationPoint>
                </DOMSymbolInstance>
              </elements>
            </DOMFrame>
            <DOMFrame index="10" duration="13" keyMode="9728">
              <elements/>
            </DOMFrame>
            <DOMFrame index="23" keyMode="9728">
              <elements>
                <DOMSymbolInstance libraryItemName="Symbol 3479" symbolType="graphic" loop="loop">
                  <transformationPoint>
                    <Point/>
                  </transformationPoint>
                </DOMSymbolInstance>
              </elements>
            </DOMFrame>
            <DOMFrame index="24" duration="13" keyMode="9728">
              <elements/>
            </DOMFrame>
            <DOMFrame index="37" keyMode="9728">
              <elements>
                <DOMSymbolInstance libraryItemName="Symbol 3492" symbolType="graphic" loop="loop">
                  <transformationPoint>
                    <Point/>
                  </transformationPoint>
                </DOMSymbolInstance>
              </elements>
            </DOMFrame>
            <DOMFrame index="38" duration="4" keyMode="9728">
              <elements/>
            </DOMFrame>
          </frames>
        </DOMLayer>
        <DOMLayer name="Layer 7" color="#D1BC46">
          <frames>
            <DOMFrame index="0" duration="8" keyMode="9728">
              <elements/>
            </DOMFrame>
            <DOMFrame index="8" keyMode="9728">
              <elements>
                <DOMSymbolInstance libraryItemName="Symbol 3465" symbolType="graphic" loop="loop">
                  <transformationPoint>
                    <Point/>
                  </transformationPoint>
                </DOMSymbolInstance>
              </elements>
            </DOMFrame>
            <DOMFrame index="9" duration="13" keyMode="9728">
              <elements/>
            </DOMFrame>
            <DOMFrame index="22" keyMode="9728">
              <elements>
                <DOMSymbolInstance libraryItemName="Symbol 3478" symbolType="graphic" loop="loop">
                  <transformationPoint>
                    <Point/>
                  </transformationPoint>
                </DOMSymbolInstance>
              </elements>
            </DOMFrame>
            <DOMFrame index="23" duration="13" keyMode="9728">
              <elements/>
            </DOMFrame>
            <DOMFrame index="36" keyMode="9728">
              <elements>
                <DOMSymbolInstance libraryItemName="Symbol 3491" symbolType="graphic" loop="loop">
                  <transformationPoint>
                    <Point/>
                  </transformationPoint>
                </DOMSymbolInstance>
              </elements>
            </DOMFrame>
            <DOMFrame index="37" duration="5" keyMode="9728">
              <elements/>
            </DOMFrame>
          </frames>
        </DOMLayer>
        <DOMLayer name="Layer 8" color="#BBF74D">
          <frames>
            <DOMFrame index="0" duration="7" keyMode="9728">
              <elements/>
            </DOMFrame>
            <DOMFrame index="7" keyMode="9728">
              <elements>
                <DOMSymbolInstance libraryItemName="Symbol 3464" symbolType="graphic" loop="loop">
                  <transformationPoint>
                    <Point/>
                  </transformationPoint>
                </DOMSymbolInstance>
              </elements>
            </DOMFrame>
            <DOMFrame index="8" duration="13" keyMode="9728">
              <elements/>
            </DOMFrame>
            <DOMFrame index="21" keyMode="9728">
              <elements>
                <DOMSymbolInstance libraryItemName="Symbol 3477" symbolType="graphic" loop="loop">
                  <transformationPoint>
                    <Point/>
                  </transformationPoint>
                </DOMSymbolInstance>
              </elements>
            </DOMFrame>
            <DOMFrame index="22" duration="13" keyMode="9728">
              <elements/>
            </DOMFrame>
            <DOMFrame index="35" keyMode="9728">
              <elements>
                <DOMSymbolInstance libraryItemName="Symbol 3490" symbolType="graphic" loop="loop">
                  <transformationPoint>
                    <Point/>
                  </transformationPoint>
                </DOMSymbolInstance>
              </elements>
            </DOMFrame>
            <DOMFrame index="36" duration="6" keyMode="9728">
              <elements/>
            </DOMFrame>
          </frames>
        </DOMLayer>
        <DOMLayer name="Layer 9" color="#C9B1E0">
          <frames>
            <DOMFrame index="0" duration="6" keyMode="9728">
              <elements/>
            </DOMFrame>
            <DOMFrame index="6" keyMode="9728">
              <elements>
                <DOMSymbolInstance libraryItemName="Symbol 3463" symbolType="graphic" loop="loop">
                  <transformationPoint>
                    <Point/>
                  </transformationPoint>
                </DOMSymbolInstance>
              </elements>
            </DOMFrame>
            <DOMFrame index="7" duration="13" keyMode="9728">
              <elements/>
            </DOMFrame>
            <DOMFrame index="20" keyMode="9728">
              <elements>
                <DOMSymbolInstance libraryItemName="Symbol 3476" symbolType="graphic" loop="loop">
                  <transformationPoint>
                    <Point/>
                  </transformationPoint>
                </DOMSymbolInstance>
              </elements>
            </DOMFrame>
            <DOMFrame index="21" duration="13" keyMode="9728">
              <elements/>
            </DOMFrame>
            <DOMFrame index="34" keyMode="9728">
              <elements>
                <DOMSymbolInstance libraryItemName="Symbol 3489" symbolType="graphic" loop="loop">
                  <transformationPoint>
                    <Point/>
                  </transformationPoint>
                </DOMSymbolInstance>
              </elements>
            </DOMFrame>
            <DOMFrame index="35" duration="7" keyMode="9728">
              <elements/>
            </DOMFrame>
          </frames>
        </DOMLayer>
        <DOMLayer name="Layer 10" color="#E8CFED">
          <frames>
            <DOMFrame index="0" duration="5" keyMode="9728">
              <elements/>
            </DOMFrame>
            <DOMFrame index="5" keyMode="9728">
              <elements>
                <DOMSymbolInstance libraryItemName="Symbol 3462" symbolType="graphic" loop="loop">
                  <transformationPoint>
                    <Point/>
                  </transformationPoint>
                </DOMSymbolInstance>
              </elements>
            </DOMFrame>
            <DOMFrame index="6" duration="13" keyMode="9728">
              <elements/>
            </DOMFrame>
            <DOMFrame index="19" keyMode="9728">
              <elements>
                <DOMSymbolInstance libraryItemName="Symbol 3475" symbolType="graphic" loop="loop">
                  <transformationPoint>
                    <Point/>
                  </transformationPoint>
                </DOMSymbolInstance>
              </elements>
            </DOMFrame>
            <DOMFrame index="20" duration="13" keyMode="9728">
              <elements/>
            </DOMFrame>
            <DOMFrame index="33" keyMode="9728">
              <elements>
                <DOMSymbolInstance libraryItemName="Symbol 3488" symbolType="graphic" loop="loop">
                  <transformationPoint>
                    <Point/>
                  </transformationPoint>
                </DOMSymbolInstance>
              </elements>
            </DOMFrame>
            <DOMFrame index="34" duration="8" keyMode="9728">
              <elements/>
            </DOMFrame>
          </frames>
        </DOMLayer>
        <DOMLayer name="Layer 11" color="#E2B46C">
          <frames>
            <DOMFrame index="0" duration="4" keyMode="9728">
              <elements/>
            </DOMFrame>
            <DOMFrame index="4" keyMode="9728">
              <elements>
                <DOMSymbolInstance libraryItemName="Symbol 3461" symbolType="graphic" loop="loop">
                  <transformationPoint>
                    <Point/>
                  </transformationPoint>
                </DOMSymbolInstance>
              </elements>
            </DOMFrame>
            <DOMFrame index="5" duration="13" keyMode="9728">
              <elements/>
            </DOMFrame>
            <DOMFrame index="18" keyMode="9728">
              <elements>
                <DOMSymbolInstance libraryItemName="Symbol 3474" symbolType="graphic" loop="loop">
                  <transformationPoint>
                    <Point/>
                  </transformationPoint>
                </DOMSymbolInstance>
              </elements>
            </DOMFrame>
            <DOMFrame index="19" duration="13" keyMode="9728">
              <elements/>
            </DOMFrame>
            <DOMFrame index="32" keyMode="9728">
              <elements>
                <DOMSymbolInstance libraryItemName="Symbol 3487" symbolType="graphic" loop="loop">
                  <transformationPoint>
                    <Point/>
                  </transformationPoint>
                </DOMSymbolInstance>
              </elements>
            </DOMFrame>
            <DOMFrame index="33" duration="9" keyMode="9728">
              <elements/>
            </DOMFrame>
          </frames>
        </DOMLayer>
        <DOMLayer name="Layer 12" color="#9FCB79">
          <frames>
            <DOMFrame index="0" duration="3" keyMode="9728">
              <elements/>
            </DOMFrame>
            <DOMFrame index="3" keyMode="9728">
              <elements>
                <DOMSymbolInstance libraryItemName="Symbol 3460" symbolType="graphic" loop="loop">
                  <transformationPoint>
                    <Point/>
                  </transformationPoint>
                </DOMSymbolInstance>
              </elements>
            </DOMFrame>
            <DOMFrame index="4" duration="13" keyMode="9728">
              <elements/>
            </DOMFrame>
            <DOMFrame index="17" keyMode="9728">
              <elements>
                <DOMSymbolInstance libraryItemName="Symbol 3473" symbolType="graphic" loop="loop">
                  <transformationPoint>
                    <Point/>
                  </transformationPoint>
                </DOMSymbolInstance>
              </elements>
            </DOMFrame>
            <DOMFrame index="18" duration="13" keyMode="9728">
              <elements/>
            </DOMFrame>
            <DOMFrame index="31" keyMode="9728">
              <elements>
                <DOMSymbolInstance libraryItemName="Symbol 3486" symbolType="graphic" loop="loop">
                  <transformationPoint>
                    <Point/>
                  </transformationPoint>
                </DOMSymbolInstance>
              </elements>
            </DOMFrame>
            <DOMFrame index="32" duration="10" keyMode="9728">
              <elements/>
            </DOMFrame>
          </frames>
        </DOMLayer>
        <DOMLayer name="Layer 13" color="#F4F46E">
          <frames>
            <DOMFrame index="0" duration="2" keyMode="9728">
              <elements/>
            </DOMFrame>
            <DOMFrame index="2" keyMode="9728">
              <elements>
                <DOMSymbolInstance libraryItemName="Symbol 3459" symbolType="graphic" loop="loop">
                  <transformationPoint>
                    <Point/>
                  </transformationPoint>
                </DOMSymbolInstance>
              </elements>
            </DOMFrame>
            <DOMFrame index="3" duration="13" keyMode="9728">
              <elements/>
            </DOMFrame>
            <DOMFrame index="16" keyMode="9728">
              <elements>
                <DOMSymbolInstance libraryItemName="Symbol 3472" symbolType="graphic" loop="loop">
                  <transformationPoint>
                    <Point/>
                  </transformationPoint>
                </DOMSymbolInstance>
              </elements>
            </DOMFrame>
            <DOMFrame index="17" duration="13" keyMode="9728">
              <elements/>
            </DOMFrame>
            <DOMFrame index="30" keyMode="9728">
              <elements>
                <DOMSymbolInstance libraryItemName="Symbol 3485" symbolType="graphic" loop="loop">
                  <transformationPoint>
                    <Point/>
                  </transformationPoint>
                </DOMSymbolInstance>
              </elements>
            </DOMFrame>
            <DOMFrame index="31" duration="11" keyMode="9728">
              <elements/>
            </DOMFrame>
          </frames>
        </DOMLayer>
        <DOMLayer name="Layer 14" color="#EAE513" current="true" isSelected="true">
          <frames>
            <DOMFrame index="0" keyMode="9728">
              <elements/>
            </DOMFrame>
            <DOMFrame index="1" keyMode="9728">
              <elements>
                <DOMSymbolInstance libraryItemName="Symbol 3458" symbolType="graphic" loop="loop">
                  <transformationPoint>
                    <Point/>
                  </transformationPoint>
                </DOMSymbolInstance>
              </elements>
            </DOMFrame>
            <DOMFrame index="2" duration="13" keyMode="9728">
              <elements/>
            </DOMFrame>
            <DOMFrame index="15" keyMode="9728">
              <elements>
                <DOMSymbolInstance libraryItemName="Symbol 3471" symbolType="graphic" loop="loop">
                  <transformationPoint>
                    <Point/>
                  </transformationPoint>
                </DOMSymbolInstance>
              </elements>
            </DOMFrame>
            <DOMFrame index="16" duration="13" keyMode="9728">
              <elements/>
            </DOMFrame>
            <DOMFrame index="29" keyMode="9728">
              <elements>
                <DOMSymbolInstance libraryItemName="Symbol 3484" symbolType="graphic" loop="loop">
                  <transformationPoint>
                    <Point/>
                  </transformationPoint>
                </DOMSymbolInstance>
              </elements>
            </DOMFrame>
            <DOMFrame index="30" duration="12" keyMode="9728">
              <elements/>
            </DOMFrame>
          </frames>
        </DOMLayer>
      </layers>
    </DOMTimeline>
  </timeline>
</DOMSymbolItem>