<DOMSymbolItem xmlns:xsi="http://www.w3.org/2001/XMLSchema-instance" xmlns="http://ns.adobe.com/xfl/2008/" name="Symbol 579" itemID="65c1d214-000023be" symbolType="graphic" lastModified="1707200124">
  <timeline>
    <DOMTimeline name="Symbol 579">
      <layers>
        <DOMLayer name="Layer 1" color="#4F4FFF" current="true" isSelected="true">
          <frames>
            <DOMFrame index="0" motionTweenScale="false" keyMode="8192">
              <elements>
                <DOMShape isFloating="true">
                  <fills>
                    <FillStyle index="1">
                      <SolidColor color="#FFFFFF"/>
                    </FillStyle>
                  </fills>
                  <edges>
                    <Edge fillStyle1="1" edges="!-620 -760|620 -760!620 -760[760 -760 760 -620!760 -620|760 619!760 619[760 759 620 759!620 759|-620 759!-620 759[-760 759 -760 619!-760 619|-760 -620!-760 -620[-760 -760 -620 -760!321 -298[342 -319 342 -349!342 -349[342 -379 321 -401
!321 -401[300 -421 270 -421!270 -421[241 -421 219 -401!219 -401|184 -365!184 -365[115 -409 36 -418!36 -418|36 -485!36 -485|82 -485!82 -485[97 -485 108 -497!108 -497[118 -507 118 -522!118 -522[118 -538 108 -548!108 -548[97 -558 82 -558
!82 -558|-82 -558!-82 -558[-98 -558 -108 -548!-108 -548[-118 -538 -118 -522!-118 -522[-118 -507 -108 -497!-108 -497[-98 -485 -82 -485!-82 -485|-36 -485!-36 -485|-36 -418!-36 -418[-165 -404 -253 -308!-253 -308[-340 -210 -340 -79!-340 -79
[-340 62 -241 162!-241 162[-141 261 0 261!0 261[141 261 241 162!241 162[340 62 340 -79!340 -79[340 -179 286 -263!286 -263|321 -298!-166 115|-159 69!-159 69|-144 32!-144 32|-122 1!-122 1|-93 -26!-93 -26|-33 -73!-33 -73|23 -116!23 -116
|43 -139!43 -139[50 -152 50 -166!50 -166[50 -191 36 -206!36 -206[23 -219 -3 -219!-3 -219[-32 -219 -46 -202!-46 -202|-60 -177!-60 -177|-65 -141!-65 -141|-159 -141!-159 -141|-153 -201!-153 -201[-146 -224 -131 -245!-131 -245[-114 -270 -82
 -286!-82 -286[-49 -300 -1 -300!-1 -300|65 -291!65 -291[93 -281 112 -262!112 -262[131 -245 140 -221!140 -221[151 -197 151 -170!151 -170|145 -132!145 -132|130 -100!130 -100|109 -75!109 -75|83 -53!83 -53|55 -32!55 -32|25 -11!25 -11|-2 10
!-2 10|-26 32!-26 32|-26 33!-26 33|152 33!152 33|152 115!152 115|-166 115"/>
                    <Edge fillStyle0="1" edges="
!-552 -70|-609 -126!-609 -126|-565 -170!-565 -170|-509 -113!-509 -113|-448 -174!-448 -174|-402 -127!-402 -127|-462 -67!-462 -67|-405 -10!-405 -10|-449 33!-449 33|-506 -23!-506 -23|-566 37!-566 37|-613 -9!-613 -9|-552 -70!-167 558|-167
 365!-167 365|-95 365!-95 365|-95 558!-95 558|-167 558!-234 440|-544 440!-544 440|-544 358!-544 358|-234 358!-234 358|-234 440!-234 557|-422 557!-422 557|-422 475!-422 475|-234 475!-234 475|-234 557"/>
                    <Edge fillStyle1="1" edges="
!545 461[545 439 430 413!430 413|315 392!315 392|269 365!269 365|-62 365!-62 365|-62 556!-62 556|269 556!269 556|315 531!315 531|430 510!430 510[545 484 545 461"/>
                  </edges>
                </DOMShape>
              </elements>
            </DOMFrame>
          </frames>
        </DOMLayer>
      </layers>
    </DOMTimeline>
  </timeline>
</DOMSymbolItem>